{
  "project_info": {
    "project_number": "1079740447946",
    "project_id": "deussenger",
    "storage_bucket": "deussenger.firebasestorage.app"
  },
  "client": [
    {
      "client_info": {
        "mobilesdk_app_id": "1:1079740447946:android:cc19dc77c3a72716a00833",
        "android_client_info": {
          "package_name": "com.example.deussenger"
        }
      },
      "oauth_client": [],
      "api_key": [
        {
          "current_key": "AIzaSyC-wMfZaJLegyMagXgCYjZWTdkMVN4RTOY"
        }
      ],
      "services": {
        "appinvite_service": {
          "other_platform_oauth_client": []
        }
      }
    }
  ],
  "configuration_version": "1"
}